spectrogrism/__init__.py
spectrogrism/distortion.py
spectrogrism/mcmc.py
spectrogrism/nisp.py
spectrogrism/polyfit.py
spectrogrism/snifs.py
spectrogrism/spectrogrism.py
spectrogrism-0.9.dist-info/LICENSE
spectrogrism-0.9.dist-info/METADATA
spectrogrism-0.9.dist-info/WHEEL
spectrogrism-0.9.dist-info/top_level.txt
spectrogrism-0.9.dist-info/RECORD
