Metadata-Version: 2.1
Name: spectrogrism
Version: 0.9
Summary: Grism-based spectrograph modeling
Home-page: https://gitlab.in2p3.fr/ycopin/spectrogrism
Author: Yannick Copin
Author-email: y.copin@ipnl.in2p3.fr
License: BSD 3-Clause License
Keywords: astronomy,astrophysics
Platform: UNKNOWN
Classifier: Development Status :: 2 - Pre-Alpha
Classifier: Intended Audience :: Science/Research
Classifier: License :: OSI Approved :: BSD License
Classifier: Programming Language :: Python :: 3
Classifier: Topic :: Scientific/Engineering :: Astronomy
Classifier: Topic :: Scientific/Engineering :: Physics
Requires-Python: >=3.6
License-File: LICENSE
Requires-Dist: astropy
Requires-Dist: iminuit (>2.0.0)
Requires-Dist: matplotlib
Requires-Dist: numpy
Requires-Dist: pandas
Requires-Dist: pyyaml
Requires-Dist: xarray
Provides-Extra: docs
Requires-Dist: nbsphinx ; extra == 'docs'
Provides-Extra: mcmc
Requires-Dist: emcee ; extra == 'mcmc'
Requires-Dist: corner ; extra == 'mcmc'
Provides-Extra: plot
Requires-Dist: mpld3 ; extra == 'plot'
Provides-Extra: tests
Requires-Dist: pytest ; extra == 'tests'
Requires-Dist: coverage ; extra == 'tests'
